django_polls_akyaaaaa-0.1.dist-info/licenses/LICENSE
polls/__init__.py
polls/admin.py
polls/apps.py
polls/models.py
polls/tests.py
polls/urls.py
polls/views.py
polls/migrations/0001_initial.py
polls/migrations/__init__.py
django_polls_akyaaaaa-0.1.dist-info/METADATA
django_polls_akyaaaaa-0.1.dist-info/WHEEL
django_polls_akyaaaaa-0.1.dist-info/top_level.txt
django_polls_akyaaaaa-0.1.dist-info/RECORD
